[{
  "SourceFile": "./Church (1 of 1).jpg",
  "ExifToolVersion": 10.40,
  "FileName": "Church (1 of 1).jpg",
  "Directory": ".",
  "FileSize": "7.9 MB",
  "FileModifyDate": "2015:01:13 20:01:04+00:00",
  "FileAccessDate": "2017:02:13 19:16:37+00:00",
  "FileInodeChangeDate": "2017:02:13 18:19:12+00:00",
  "FilePermissions": "rw-r--r--",
  "FileType": "JPEG",
  "FileTypeExtension": "jpg",
  "MIMEType": "image/jpeg",
  "ExifByteOrder": "Little-endian (Intel, II)",
  "Model": "NIKON D7000",
  "XResolution": 240,
  "YResolution": 240,
  "ResolutionUnit": "inches",
  "Software": "Adobe Photoshop Lightroom 4.4 (Windows)",
  "ModifyDate": "2015:01:13 20:01:03",
  "ExposureTime": "1/50",
  "FNumber": 16.0,
  "ISO": 100,
  "ExifVersion": "0230",
  "DateTimeOriginal": "2012:12:07 14:20:29",
  "CreateDate": "2012:12:07 14:20:29",
  "ShutterSpeedValue": "1/50",
  "ApertureValue": 16.0,
  "FocalLength": "18.0 mm",
  "Compression": "JPEG (old-style)",
  "ThumbnailOffset": 486,
  "ThumbnailLength": 8819,
  "DisplayedUnitsX": "inches",
  "DisplayedUnitsY": "inches",
  "CurrentIPTCDigest": "6f4f1d557dadb282e02b7173cdc723b3",
  "CodedCharacterSet": "UTF8",
  "ApplicationRecordVersion": 4,
  "TimeCreated": "14:20:29",
  "DigitalCreationDate": "2012:12:07",
  "DigitalCreationTime": "14:20:29+00:00",
  "PhotoshopThumbnail": "(Binary data 8819 bytes, use -b option to extract)",
  "IPTCDigest": "6f4f1d557dadb282e02b7173cdc723b3",
  "ProfileCMMType": "Lino",
  "ProfileVersion": "2.1.0",
  "ProfileClass": "Display Device Profile",
  "ColorSpaceData": "RGB ",
  "ProfileConnectionSpace": "XYZ ",
  "ProfileDateTime": "1998:02:09 06:49:00",
  "ProfileFileSignature": "acsp",
  "PrimaryPlatform": "Microsoft Corporation",
  "CMMFlags": "Not Embedded, Independent",
  "DeviceManufacturer": "IEC ",
  "DeviceModel": "sRGB",
  "DeviceAttributes": "Reflective, Glossy, Positive, Color",
  "RenderingIntent": "Perceptual",
  "ConnectionSpaceIlluminant": "0.9642 1 0.82491",
  "ProfileCreator": "HP  ",
  "ProfileID": 0,
  "ProfileCopyright": "Copyright (c) 1998 Hewlett-Packard Company",
  "ProfileDescription": "sRGB IEC61966-2.1",
  "MediaWhitePoint": "0.95045 1 1.08905",
  "MediaBlackPoint": "0 0 0",
  "RedMatrixColumn": "0.43607 0.22249 0.01392",
  "GreenMatrixColumn": "0.38515 0.71687 0.09708",
  "BlueMatrixColumn": "0.14307 0.06061 0.7141",
  "DeviceMfgDesc": "IEC http://www.iec.ch",
  "DeviceModelDesc": "IEC 61966-2.1 Default RGB colour space - sRGB",
  "ViewingCondDesc": "Reference Viewing Condition in IEC61966-2.1",
  "ViewingCondIlluminant": "19.6445 20.3718 16.8089",
  "ViewingCondSurround": "3.92889 4.07439 3.36179",
  "ViewingCondIlluminantType": "D50",
  "Luminance": "76.03647 80 87.12462",
  "MeasurementObserver": "CIE 1931",
  "MeasurementBacking": "0 0 0",
  "MeasurementGeometry": "Unknown",
  "MeasurementFlare": "0.999%",
  "MeasurementIlluminant": "D65",
  "Technology": "Cathode Ray Tube Display",
  "RedTRC": "(Binary data 2060 bytes, use -b option to extract)",
  "GreenTRC": "(Binary data 2060 bytes, use -b option to extract)",
  "BlueTRC": "(Binary data 2060 bytes, use -b option to extract)",
  "XMPToolkit": "Adobe XMP Core 5.5-c002 1.148022, 2012/07/15-18:06:45        ",
  "Method": "Details Enhancer",
  "Strength": 100.0,
  "ColorSaturation": 80.0,
  "Luminosity": 10.0,
  "WhiteClip": 1.124050,
  "BlackClip": 0.002900,
  "SmoothingMode": "Light",
  "Smoothing": "High    ",
  "Microcontrast": 10.0,
  "Microsmoothing": 1.5,
  "Gamma": 0.90,
  "HighlightsSmoothing": 0.0,
  "ShadowsSmoothing": 0.0,
  "ShadowsClipping": 0.0,
  "ColorTemperature": 0.0,
  "SaturationHighlights": 10.0,
  "SaturationShadows": -3.0,
  "IsPano360": "No ",
  "CreatorTool": "Adobe Photoshop Lightroom 4.4 (Windows)",
  "MetadataDate": "2015:01:13 20:01:03Z",
  "DateCreated": "2012:12:07 14:20:29",
  "DocumentID": "xmp.did:8304fecc-3f12-4e45-a961-1f7a26759acf",
  "OriginalDocumentID": "F737C511D7BE7BC790D422B8EC7ED70F",
  "InstanceID": "xmp.iid:8304fecc-3f12-4e45-a961-1f7a26759acf",
  "Format": "image/jpeg",
  "Version": 7.4,
  "ProcessVersion": 6.7,
  "WhiteBalance": "Custom",
  "IncrementalTemperature": -20,
  "IncrementalTint": -35,
  "Saturation": -30,
  "Sharpness": 25,
  "LuminanceSmoothing": 0,
  "ColorNoiseReduction": 25,
  "VignetteAmount": 0,
  "ShadowTint": 0,
  "RedHue": 0,
  "RedSaturation": 0,
  "GreenHue": 0,
  "GreenSaturation": 0,
  "BlueHue": 0,
  "BlueSaturation": 0,
  "Vibrance": -10,
  "HueAdjustmentRed": 0,
  "HueAdjustmentOrange": 0,
  "HueAdjustmentYellow": 0,
  "HueAdjustmentGreen": 0,
  "HueAdjustmentAqua": 0,
  "HueAdjustmentBlue": 0,
  "HueAdjustmentPurple": 0,
  "HueAdjustmentMagenta": 0,
  "SaturationAdjustmentRed": -60,
  "SaturationAdjustmentOrange": -55,
  "SaturationAdjustmentYellow": -50,
  "SaturationAdjustmentGreen": -70,
  "SaturationAdjustmentAqua": -60,
  "SaturationAdjustmentBlue": -40,
  "SaturationAdjustmentPurple": -55,
  "SaturationAdjustmentMagenta": -20,
  "LuminanceAdjustmentRed": "+20",
  "LuminanceAdjustmentOrange": "+20",
  "LuminanceAdjustmentYellow": "+20",
  "LuminanceAdjustmentGreen": "+20",
  "LuminanceAdjustmentAqua": "+20",
  "LuminanceAdjustmentBlue": "+20",
  "LuminanceAdjustmentPurple": "+20",
  "LuminanceAdjustmentMagenta": "+20",
  "SplitToningShadowHue": 0,
  "SplitToningShadowSaturation": 0,
  "SplitToningHighlightHue": 0,
  "SplitToningHighlightSaturation": 0,
  "SplitToningBalance": 0,
  "ParametricShadows": 0,
  "ParametricDarks": 0,
  "ParametricLights": 0,
  "ParametricHighlights": 0,
  "ParametricShadowSplit": 25,
  "ParametricMidtoneSplit": 50,
  "ParametricHighlightSplit": 75,
  "SharpenRadius": "+1.0",
  "SharpenDetail": 25,
  "SharpenEdgeMasking": 0,
  "PostCropVignetteAmount": 0,
  "GrainAmount": 0,
  "ColorNoiseReductionDetail": 50,
  "LensProfileEnable": 0,
  "LensManualDistortionAmount": 0,
  "PerspectiveVertical": 0,
  "PerspectiveHorizontal": 0,
  "PerspectiveRotate": 0.0,
  "PerspectiveScale": 100,
  "AutoLateralCA": 0,
  "Exposure2012": -5.00,
  "Contrast2012": -45,
  "Highlights2012": "+100",
  "Shadows2012": 0,
  "Whites2012": "+79",
  "Blacks2012": "+31",
  "Clarity2012": "+20",
  "DefringePurpleAmount": 0,
  "DefringePurpleHueLo": 30,
  "DefringePurpleHueHi": 70,
  "DefringeGreenAmount": 0,
  "DefringeGreenHueLo": 40,
  "DefringeGreenHueHi": 60,
  "ConvertToGrayscale": false,
  "ToneCurveName2012": "Linear",
  "CameraProfile": "Adobe Standard",
  "LensProfileSetup": "LensDefaults",
  "HasSettings": true,
  "HasCrop": false,
  "AlreadyApplied": true,
  "DocumentAncestors": "xmp.did:86fec298-ea96-6044-9601-0ea6fb803f2d",
  "HistoryAction": ["derived","saved","saved","saved","saved","saved","saved","derived","saved"],
  "HistoryParameters": ["converted from image/tiff to image/jpeg, saved to new location","saved to new location"],
  "HistoryInstanceID": ["xmp.iid:e421bc26-f6b0-6c4d-ac45-bda849728499","xmp.iid:500B6BA7E443E31183CBDF3A01909CC7","xmp.iid:510B6BA7E443E31183CBDF3A01909CC7","xmp.iid:520B6BA7E443E31183CBDF3A01909CC7","xmp.iid:530B6BA7E443E31183CBDF3A01909CC7","xmp.iid:540B6BA7E443E31183CBDF3A01909CC7","xmp.iid:8304fecc-3f12-4e45-a961-1f7a26759acf"],
  "HistoryWhen": ["2013:10:26 14:32:05+01:00","2013:11:02 19:17:24Z","2013:11:02 19:17:24Z","2013:11:02 19:19:03Z","2013:11:02 19:19:03Z","2013:11:02 19:23:13Z","2015:01:13 20:01:03Z"],
  "HistorySoftwareAgent": ["Adobe Photoshop Lightroom 4.4 (Windows)","Adobe Photoshop CS5 Windows","Adobe Photoshop CS5 Windows","Adobe Photoshop CS5 Windows","Adobe Photoshop CS5 Windows","Adobe Photoshop CS5 Windows","Adobe Photoshop Lightroom 4.4 (Windows)"],
  "HistoryChanged": ["/","/","/","/","/","/","/"],
  "DerivedFromInstanceID": "xmp.iid:540B6BA7E443E31183CBDF3A01909CC7",
  "DerivedFromDocumentID": "xmp.did:e421bc26-f6b0-6c4d-ac45-bda849728499",
  "DerivedFromOriginalDocumentID": "F737C511D7BE7BC790D422B8EC7ED70F",
  "ToneCurvePV2012": ["0, 0","255, 255"],
  "ToneCurvePV2012Red": ["0, 0","255, 255"],
  "ToneCurvePV2012Green": ["0, 0","255, 255"],
  "ToneCurvePV2012Blue": ["0, 0","255, 255"],
  "PaintCorrectionWhat": "Correction",
  "PaintCorrectionAmount": 1.000000,
  "PaintCorrectionActive": true,
  "PaintCorrectionSharpness": 0.000000,
  "PaintCorrectionBrightness": 0.000000,
  "PaintCorrectionHue": 0.000000,
  "PaintCorrectionSaturation": 0.000000,
  "PaintCorrectionExposure2012": 0.000000,
  "PaintCorrectionContrast2012": 0.000000,
  "PaintCorrectionHighlights2012": 0.000000,
  "PaintCorrectionShadows2012": 0.000000,
  "PaintCorrectionClarity2012": 0.000000,
  "PaintCorrectionLuminanceNoise": 0.000000,
  "PaintCorrectionMoire": 0.000000,
  "PaintCorrectionDefringe": 0.000000,
  "PaintCorrectionTemperature": 0.000000,
  "PaintCorrectionTint": 0.000000,
  "PaintCorrectionMaskWhat": "Mask/Paint",
  "PaintCorrectionMaskValue": 1.000000,
  "PaintCorrectionMaskRadius": 0.074621,
  "PaintCorrectionMaskFlow": 0.422000,
  "PaintCorrectionMaskCenterWeight": 0.137873,
  "PaintCorrectionMaskDabs": "d 0.508561 0.582633",
  "GradientBasedCorrWhat": "Correction",
  "GradientBasedCorrAmount": 1.000000,
  "GradientBasedCorrActive": true,
  "GradientBasedCorrSharpness": 0.000000,
  "GradientBasedCorrBrightness": 0.000000,
  "GradientBasedCorrHue": 0.000000,
  "GradientBasedCorrSaturation": 0.000000,
  "GradientBasedCorrExposure2012": -0.103500,
  "GradientBasedCorrContrast2012": 0.000000,
  "GradientBasedCorrHighlights2012": 0.000000,
  "GradientBasedCorrShadows2012": 0.000000,
  "GradientBasedCorrClarity2012": 0.000000,
  "GradientBasedCorrLuminanceNoise": 0.000000,
  "GradientBasedCorrMoire": 0.000000,
  "GradientBasedCorrDefringe": 0.000000,
  "GradientBasedCorrTemperature": 0.000000,
  "GradientBasedCorrTint": 0.000000,
  "GradientBasedCorrMaskWhat": "Mask/Gradient",
  "GradientBasedCorrMaskValue": 1.000000,
  "GradientBasedCorrMaskZeroX": 0.513146,
  "GradientBasedCorrMaskZeroY": 0.752101,
  "GradientBasedCorrMaskFullX": 0.494107,
  "GradientBasedCorrMaskFullY": 0.074230,
  "DCTEncodeVersion": 100,
  "APP14Flags0": "[14]",
  "APP14Flags1": "(none)",
  "ColorTransform": "YCbCr",
  "ImageWidth": 5273,
  "ImageHeight": 3412,
  "EncodingProcess": "Baseline DCT, Huffman coding",
  "BitsPerSample": 8,
  "ColorComponents": 3,
  "YCbCrSubSampling": "YCbCr4:4:4 (1 1)",
  "Aperture": 16.0,
  "DateTimeCreated": "2012:12:07 14:20:29",
  "DigitalCreationDateTime": "2012:12:07 14:20:29+00:00",
  "ImageSize": "5273x3412",
  "Megapixels": 18.0,
  "ShutterSpeed": "1/50",
  "ThumbnailImage": "(Binary data 8819 bytes, use -b option to extract)",
  "FocalLength35efl": "18.0 mm",
  "LightValue": 13.6
}]
